langchain_kozmograph/__init__.py
langchain_kozmograph/chains/__init__.py
langchain_kozmograph/chains/graph_qa.py
langchain_kozmograph/chains/prompts.py
langchain_kozmograph/document_loaders.py
langchain_kozmograph/graphs/__init__.py
langchain_kozmograph/graphs/graph_document.py
langchain_kozmograph/graphs/graph_store.py
langchain_kozmograph/graphs/kozmograph.py
langchain_kozmograph/py.typed
langchain_kozmograph/retrievers.py
langchain_kozmograph/toolkits.py
langchain_kozmograph/tools.py
langchain_kozmograph-0.1.1.dist-info/LICENSE
langchain_kozmograph-0.1.1.dist-info/METADATA
langchain_kozmograph-0.1.1.dist-info/WHEEL
langchain_kozmograph-0.1.1.dist-info/RECORD
